fLZc_python/README.md
fLZc_python/__init__.py
fLZc_python/core/LZ76c.c
fLZc_python/core/LZ76c.h
fLZc_python/core/LZ78c.c
fLZc_python/core/LZ78c.h
fLZc_python/core/khashl.h
fLZc_python/core/utils.c
fLZc_python/core/utils.h
fLZc_python/examples/__init__.py
fLZc_python/examples/lzc_demo.py
fLZc_python/liblzc.dylib
fLZc_python/python_wrapper/LZc_binarise.py
fLZc_python/python_wrapper/LZc_normfac.py
fLZc_python/python_wrapper/__init__.py
fLZc_python/python_wrapper/flzc.py
flzc-0.1.5.dist-info/METADATA
flzc-0.1.5.dist-info/WHEEL
flzc-0.1.5.dist-info/licenses/LICENSE
flzc-0.1.5.dist-info/RECORD
