Metadata-Version: 2.2
Name: fLZc
Version: 0.1.5
Summary: Python wrapper for fLZc complexity measure (based on https://github.com/lcbarnett/fLZc)
Author-Email: Romy Beaute & Lionel Barnett <r.beaut@sussex.ac.uk>
License: MIT
Requires-Python: >=3.8
Requires-Dist: numpy
